vadslice/__init__.py
vadslice/cli.py
vadslice/core.py
vadslice/py.typed
vadslice/silero_onnx_vad.py
vadslice/silero_vad.onnx
vadslice-1.1.0.dist-info/WHEEL
vadslice-1.1.0.dist-info/entry_points.txt
vadslice-1.1.0.dist-info/METADATA
vadslice-1.1.0.dist-info/RECORD
