Metadata-Version: 2.3
Name: vadslice
Version: 1.1.0
Summary: Slices audio clips into chunks of a specific number of seconds at the closest moment of silence (decided by silero-vad). Uses onnx which avoids the pytorch dependency.
Author: bn-l
Author-email: bn-l <13162197+bn-l@users.noreply.github.com>
Requires-Dist: av>=16.0.1
Requires-Dist: loguru>=0.7.3
Requires-Dist: numpy>=2.3.5
Requires-Dist: onnxruntime>=1.23.2
Requires-Python: >=3.12
Project-URL: Homepage, https://github.com/bn-l/vadslice
Project-URL: Repository, https://github.com/bn-l/vadslice
Project-URL: Issues, https://github.com/bn-l/vadslice/issues
